pieql/__init__.py
pieql-0.0.2.dist-info/METADATA
pieql-0.0.2.dist-info/WHEEL
pieql-0.0.2.dist-info/top_level.txt
pieql-0.0.2.dist-info/zip-safe
pieql-0.0.2.dist-info/RECORD
