Metadata-Version: 2.4
Name: pieql
Version: 0.0.2
Summary: QL wrapper on top of existing FastAPI web service
Home-page: https://github.com/PieDataLabs/pieql.git
Author: George Kasparyants
Author-email: gkasparyants@gmail.com
License: 
Classifier: Intended Audience :: Developers
Classifier: Operating System :: OS Independent
Classifier: Topic :: Software Development :: Libraries :: Python Modules
Classifier: Programming Language :: Python
Classifier: Programming Language :: Python :: 3 :: Only
Classifier: Programming Language :: Python :: 3.6
Requires-Python: >=3.6
Requires-Dist: jmespath
Requires-Dist: fastapi
Dynamic: author
Dynamic: author-email
Dynamic: classifier
Dynamic: home-page
Dynamic: license
Dynamic: requires-dist
Dynamic: requires-python
Dynamic: summary
